{
  "project_info": {
    "project_number": "553720186976",
    "project_id": "caysa-2",
    "storage_bucket": "caysa-2.appspot.com"
  },
  "client": [
    {
      "client_info": {
        "mobilesdk_app_id": "1:553720186976:android:367121e47a697438115b05",
        "android_client_info": {
          "package_name": "com.example.caysa2021"
        }
      },
      "oauth_client": [
        {
          "client_id": "553720186976-nbo73u4ria3aukrmoffor53pfb3f6ik5.apps.googleusercontent.com",
          "client_type": 1,
          "android_info": {
            "package_name": "com.example.caysa2021",
            "certificate_hash": "cb29544fd4c5ba41f6d9b8f56018345b4ce833e3"
          }
        },
        {
          "client_id": "553720186976-bqmuft26ieicr34hbpuhqv4t5jki57ne.apps.googleusercontent.com",
          "client_type": 3
        }
      ],
      "api_key": [
        {
          "current_key": "AIzaSyABexo3NjJfKdbyKr3WlUS34NTYZYf9TrI"
        }
      ],
      "services": {
        "appinvite_service": {
          "other_platform_oauth_client": [
            {
              "client_id": "553720186976-bqmuft26ieicr34hbpuhqv4t5jki57ne.apps.googleusercontent.com",
              "client_type": 3
            }
          ]
        }
      }
    }
  ],
  "configuration_version": "1"
}